mimiqlink/__init__.py
mimiqlink/abstractconnection.py
mimiqlink/handler.py
mimiqlink/infos.py
mimiqlink/mimiqconnection.py
mimiqlink/planqkconnection.py
mimiqlink/public/assets/HelpView-5f099904.js
mimiqlink/public/assets/index-234ddc04.js
mimiqlink/public/assets/index-5d5ce95c.css
mimiqlink/public/assets/logo-141cb000.svg
mimiqlink/public/favicon.ico
mimiqlink/public/index.html
mimiqlink/utils.py
mimiqlink-0.8.2.dist-info/AUTHORS.md
mimiqlink-0.8.2.dist-info/LICENSE
mimiqlink-0.8.2.dist-info/METADATA
mimiqlink-0.8.2.dist-info/WHEEL
mimiqlink-0.8.2.dist-info/RECORD
