Metadata-Version: 2.3
Name: mimiqlink
Version: 0.8.2
Summary: Core client library for the QPerfect MIMIQ Cloud API
License: Apache-2.0
Author: Guido Masella
Author-email: guido.masella@qperfect.io
Requires-Python: >=3.9,<4
Classifier: License :: OSI Approved :: Apache Software License
Classifier: Programming Language :: Python :: 3
Classifier: Programming Language :: Python :: 3.9
Classifier: Programming Language :: Python :: 3.10
Classifier: Programming Language :: Python :: 3.11
Classifier: Programming Language :: Python :: 3.12
Classifier: Programming Language :: Python :: 3.13
Requires-Dist: requests (>=2.31,<3)
Project-URL: Documentation, https://docs.qperfect.io
Project-URL: Repository, https://github.com/qperfect-io/mimiqcircuits-python
